karrio/mappers/purolator/__init__.py
karrio/mappers/purolator/mapper.py
karrio/mappers/purolator/proxy.py
karrio/mappers/purolator/settings.py
karrio/plugins/purolator/__init__.py
karrio/providers/purolator/__init__.py
karrio/providers/purolator/address.py
karrio/providers/purolator/error.py
karrio/providers/purolator/rate.py
karrio/providers/purolator/tracking.py
karrio/providers/purolator/units.py
karrio/providers/purolator/utils.py
karrio/providers/purolator/pickup/__init__.py
karrio/providers/purolator/pickup/cancel.py
karrio/providers/purolator/pickup/create.py
karrio/providers/purolator/pickup/update.py
karrio/providers/purolator/pickup/validate.py
karrio/providers/purolator/shipment/__init__.py
karrio/providers/purolator/shipment/cancel.py
karrio/providers/purolator/shipment/create.py
karrio/providers/purolator/shipment/documents.py
karrio/schemas/purolator/__init__.py
karrio/schemas/purolator/array_ofstring.py
karrio/schemas/purolator/data_types.py
karrio/schemas/purolator/estimate_service_2_1_2.py
karrio/schemas/purolator/freight_data_types.py
karrio/schemas/purolator/freight_estimate_service_1_1_0.py
karrio/schemas/purolator/freight_pickup_service_1_1_0.py
karrio/schemas/purolator/freight_shipment_service_1_1_0.py
karrio/schemas/purolator/freight_tracking_service_1_1_0.py
karrio/schemas/purolator/freight_validation_detail.py
karrio/schemas/purolator/freight_validation_fault.py
karrio/schemas/purolator/locator_service_1_0_2.py
karrio/schemas/purolator/pickup_service_1_2_1.py
karrio/schemas/purolator/returns_management_service_2_0.py
karrio/schemas/purolator/service_availability_service_2_0_2.py
karrio/schemas/purolator/shipping_documents_service_1_3_0.py
karrio/schemas/purolator/shipping_service_2_1_3.py
karrio/schemas/purolator/tracking_service_1_2_2.py
karrio/schemas/purolator/validation_detail.py
karrio/schemas/purolator/validation_fault.py
karrio_purolator-2026.1.4.dist-info/METADATA
karrio_purolator-2026.1.4.dist-info/WHEEL
karrio_purolator-2026.1.4.dist-info/entry_points.txt
karrio_purolator-2026.1.4.dist-info/top_level.txt
karrio_purolator-2026.1.4.dist-info/RECORD
